package/RB.py
package/__init__.py
package/main_tests.py
package/toBayes.py
Lab2_IA-0.0.13.dist-info/METADATA
Lab2_IA-0.0.13.dist-info/WHEEL
Lab2_IA-0.0.13.dist-info/top_level.txt
Lab2_IA-0.0.13.dist-info/RECORD
