Metadata-Version: 2.1
Name: Lab2-IA
Version: 0.0.13
Summary: R bayesianas
Author: Maria Isabel Solano,Roberto Vallecillos, Diego Cordova, Alejandro Gomez
Keywords: python,bayesian,statistics
Classifier: Development Status :: 1 - Planning
Classifier: Intended Audience :: Developers
Classifier: Programming Language :: Python :: 3
Classifier: Operating System :: Unix
Classifier: Operating System :: MacOS :: MacOS X
Classifier: Operating System :: Microsoft :: Windows
Requires-Dist: opencv-python
Requires-Dist: pyautogui
Requires-Dist: pyaudio
